{
  "sourceId": "cfbd-portal-v1",
  "sourceType": "cfbd-portal",
  "team": "Pittsburgh Panthers",
  "years": [
    2024,
    2025,
    2026
  ],
  "provenance": {
    "sources": [
      {
        "name": "CFBD player/portal 2024",
        "endpoint": "/player/portal?year=2024"
      },
      {
        "name": "CFBD player/portal 2025",
        "endpoint": "/player/portal?year=2025"
      },
      {
        "name": "CFBD player/portal 2026",
        "endpoint": "/player/portal?year=2026"
      }
    ],
    "collectedAt": "2026-07-04T12:26:48.398Z",
    "collectorVersion": "2ba6b68",
    "dataSeason": 2026,
    "dataCutoff": null
  },
  "entries": [
    {
      "name": "Josh McCarty",
      "position": "S",
      "origin": "Eastern Michigan",
      "destination": "Pittsburgh",
      "rating": null,
      "stars": 2,
      "eligibility": "Immediate",
      "transferDate": "2024-04-17T18:43:00.000Z",
      "season": 2024
    },
    {
      "name": "Raphael Williams Jr.",
      "position": "WR",
      "origin": "San Diego State",
      "destination": "Pittsburgh",
      "rating": 0.89,
      "stars": 3,
      "eligibility": "Immediate",
      "transferDate": "2023-12-29T06:00:00.000Z",
      "season": 2024
    },
    {
      "name": "Jaremiah Anglin Jr.",
      "position": "S",
      "origin": "Kentucky",
      "destination": "Pittsburgh",
      "rating": 0.87,
      "stars": 3,
      "eligibility": "Immediate",
      "transferDate": "2024-04-23T15:56:00.000Z",
      "season": 2024
    },
    {
      "name": "Nate Matlack",
      "position": "EDGE",
      "origin": "Kansas State",
      "destination": "Pittsburgh",
      "rating": 0.87,
      "stars": 3,
      "eligibility": "Immediate",
      "transferDate": "2023-12-04T20:10:00.000Z",
      "season": 2024
    },
    {
      "name": "Desmond Reid",
      "position": "RB",
      "origin": "Western Carolina",
      "destination": "Pittsburgh",
      "rating": 0.87,
      "stars": 3,
      "eligibility": "Immediate",
      "transferDate": "2023-12-06T18:01:00.000Z",
      "season": 2024
    },
    {
      "name": "Eli Holstein",
      "position": "QB",
      "origin": "Alabama",
      "destination": "Pittsburgh",
      "rating": 0.88,
      "stars": 3,
      "eligibility": "Immediate",
      "transferDate": "2024-01-03T21:47:00.000Z",
      "season": 2024
    },
    {
      "name": "David Ojiegbe",
      "position": "EDGE",
      "origin": "Clemson",
      "destination": "Pittsburgh",
      "rating": 0.89,
      "stars": 3,
      "eligibility": "Immediate",
      "transferDate": "2023-12-05T17:10:00.000Z",
      "season": 2024
    },
    {
      "name": "Keye Thompson",
      "position": "LB",
      "origin": "Ohio",
      "destination": "Pittsburgh",
      "rating": 0.88,
      "stars": 3,
      "eligibility": "Immediate",
      "transferDate": "2023-12-09T21:16:00.000Z",
      "season": 2024
    },
    {
      "name": "Jake Overman",
      "position": "TE",
      "origin": "Oregon State",
      "destination": "Pittsburgh",
      "rating": 0.86,
      "stars": 3,
      "eligibility": "Immediate",
      "transferDate": "2023-09-25T14:53:00.000Z",
      "season": 2024
    },
    {
      "name": "Anthony Johnson",
      "position": "DL",
      "origin": "Illinois",
      "destination": "Pittsburgh",
      "rating": 0.85,
      "stars": 3,
      "eligibility": "Immediate",
      "transferDate": "2024-04-14T02:10:00.000Z",
      "season": 2024
    },
    {
      "name": "Tamon Lynum",
      "position": "CB",
      "origin": "Nebraska",
      "destination": "Pittsburgh",
      "rating": 0.85,
      "stars": 3,
      "eligibility": "Immediate",
      "transferDate": "2023-12-07T17:06:00.000Z",
      "season": 2024
    },
    {
      "name": "Nick James",
      "position": "DL",
      "origin": "Indiana",
      "destination": "Pittsburgh",
      "rating": 0.85,
      "stars": 3,
      "eligibility": "Immediate",
      "transferDate": "2023-11-27T17:43:00.000Z",
      "season": 2024
    },
    {
      "name": "Chief Borders",
      "position": "EDGE",
      "origin": "Nebraska",
      "destination": "Pittsburgh",
      "rating": 0.85,
      "stars": 3,
      "eligibility": "Immediate",
      "transferDate": "2024-04-29T20:58:00.000Z",
      "season": 2024
    },
    {
      "name": "Lyndon Cooper",
      "position": "IOL",
      "origin": "NC State",
      "destination": "Pittsburgh",
      "rating": 0.84,
      "stars": 3,
      "eligibility": "Immediate",
      "transferDate": "2023-12-04T13:44:00.000Z",
      "season": 2024
    },
    {
      "name": "Kavir Bains-Marquez",
      "position": "S",
      "origin": "UC Davis",
      "destination": "Pittsburgh",
      "rating": 0.86,
      "stars": 3,
      "eligibility": "Immediate",
      "transferDate": "2025-01-05T17:27:00.000Z",
      "season": 2025
    },
    {
      "name": "Zion Ferguson",
      "position": "CB",
      "origin": "North Carolina",
      "destination": "Pittsburgh",
      "rating": 0.86,
      "stars": 3,
      "eligibility": "Immediate",
      "transferDate": "2025-04-24T19:53:00.000Z",
      "season": 2025
    },
    {
      "name": "Kendall Stanley",
      "position": "OT",
      "origin": "Charlotte",
      "destination": "Pittsburgh",
      "rating": 0.86,
      "stars": 3,
      "eligibility": "Immediate",
      "transferDate": "2024-12-23T22:03:00.000Z",
      "season": 2025
    },
    {
      "name": "Justin Holmes",
      "position": "TE",
      "origin": "Marshall",
      "destination": "Pittsburgh",
      "rating": 0.83,
      "stars": 3,
      "eligibility": "Immediate",
      "transferDate": "2025-04-25T12:04:00.000Z",
      "season": 2025
    },
    {
      "name": "Deuce Spann",
      "position": "WR",
      "origin": "Florida State",
      "destination": "Pittsburgh",
      "rating": 0.87,
      "stars": 3,
      "eligibility": "Immediate",
      "transferDate": "2024-12-20T14:29:00.000Z",
      "season": 2025
    },
    {
      "name": "Ty Banco",
      "position": "IOL",
      "origin": "Texas A&M",
      "destination": "Pittsburgh",
      "rating": null,
      "stars": null,
      "eligibility": "Immediate",
      "transferDate": "2025-04-23T20:19:00.000Z",
      "season": 2025
    },
    {
      "name": "Cole Gonzales",
      "position": "QB",
      "origin": "Oklahoma",
      "destination": "Pittsburgh",
      "rating": 0.85,
      "stars": 3,
      "eligibility": "Immediate",
      "transferDate": "2025-04-24T12:59:00.000Z",
      "season": 2025
    },
    {
      "name": "Keith Gouveia",
      "position": "IOL",
      "origin": "Richmond",
      "destination": "Pittsburgh",
      "rating": 0.86,
      "stars": 3,
      "eligibility": "Immediate",
      "transferDate": "2025-01-05T02:12:00.000Z",
      "season": 2025
    },
    {
      "name": "Jayden Bonsu",
      "position": "S",
      "origin": "Ohio State",
      "destination": "Pittsburgh",
      "rating": 0.85,
      "stars": 3,
      "eligibility": "Immediate",
      "transferDate": "2025-01-04T19:43:00.000Z",
      "season": 2025
    },
    {
      "name": "Rashan Murray",
      "position": "CB",
      "origin": "PennWest California",
      "destination": "Pittsburgh",
      "rating": 0.86,
      "stars": 3,
      "eligibility": "Immediate",
      "transferDate": "2025-01-05T00:04:00.000Z",
      "season": 2025
    },
    {
      "name": "Blaine Spires",
      "position": "EDGE",
      "origin": "Utah State",
      "destination": "Pittsburgh",
      "rating": 0.87,
      "stars": 3,
      "eligibility": "Immediate",
      "transferDate": "2025-01-04T16:54:00.000Z",
      "season": 2025
    },
    {
      "name": "Jeff Persi",
      "position": "OT",
      "origin": "Michigan",
      "destination": "Pittsburgh",
      "rating": 0.85,
      "stars": 3,
      "eligibility": "Immediate",
      "transferDate": "2025-01-27T21:04:00.000Z",
      "season": 2025
    },
    {
      "name": "Joey Zelinsky",
      "position": "EDGE",
      "origin": "Eastern Michigan",
      "destination": "Pittsburgh",
      "rating": 0.85,
      "stars": 3,
      "eligibility": "Immediate",
      "transferDate": "2025-01-05T03:36:00.000Z",
      "season": 2025
    },
    {
      "name": "Jaeden Moore",
      "position": "EDGE",
      "origin": "Oregon",
      "destination": "Pittsburgh",
      "rating": 0.86,
      "stars": 3,
      "eligibility": "Immediate",
      "transferDate": "2025-01-07T20:58:00.000Z",
      "season": 2025
    },
    {
      "name": "Cataurus Hicks",
      "position": "WR",
      "origin": "Louisville",
      "destination": "Pittsburgh",
      "rating": 0.87,
      "stars": 3,
      "eligibility": "Immediate",
      "transferDate": "2025-01-10T02:59:00.000Z",
      "season": 2025
    },
    {
      "name": "Carson Kent",
      "position": "TE",
      "origin": "Oklahoma",
      "destination": "Pittsburgh",
      "rating": 0.87,
      "stars": 3,
      "eligibility": "Immediate",
      "transferDate": "2026-01-09T23:46:00.000Z",
      "season": 2026
    },
    {
      "name": "Jeremiah Warren",
      "position": "DL",
      "origin": "Illinois",
      "destination": "Pittsburgh",
      "rating": 0.86,
      "stars": 3,
      "eligibility": "Immediate",
      "transferDate": "2026-01-10T16:36:00.000Z",
      "season": 2026
    },
    {
      "name": "Justin Schmidt",
      "position": "LS",
      "origin": "Purdue",
      "destination": "Pittsburgh",
      "rating": null,
      "stars": 2,
      "eligibility": "Immediate",
      "transferDate": "2026-01-09T23:44:00.000Z",
      "season": 2026
    },
    {
      "name": "Raion Strader",
      "position": "CB",
      "origin": "Auburn",
      "destination": "Pittsburgh",
      "rating": 0.87,
      "stars": 3,
      "eligibility": "Immediate",
      "transferDate": "2026-01-08T16:41:46.000Z",
      "season": 2026
    },
    {
      "name": "Samuel Hunsaker",
      "position": "K",
      "origin": "Northern Arizona",
      "destination": "Pittsburgh",
      "rating": 0.83,
      "stars": 3,
      "eligibility": "Immediate",
      "transferDate": "2026-01-14T01:34:49.000Z",
      "season": 2026
    },
    {
      "name": "La'Vell Wright",
      "position": "RB",
      "origin": "Western Kentucky",
      "destination": "Pittsburgh",
      "rating": 0.85,
      "stars": 3,
      "eligibility": "Immediate",
      "transferDate": "2026-01-10T15:03:00.000Z",
      "season": 2026
    },
    {
      "name": "DeMarco Ward",
      "position": "LB",
      "origin": "Memphis",
      "destination": "Pittsburgh",
      "rating": 0.85,
      "stars": 3,
      "eligibility": "Immediate",
      "transferDate": "2026-01-10T23:39:00.000Z",
      "season": 2026
    },
    {
      "name": "Kanye Thompson",
      "position": "CB",
      "origin": "Slippery Rock",
      "destination": "Pittsburgh",
      "rating": 0.85,
      "stars": 3,
      "eligibility": "Immediate",
      "transferDate": "2026-01-08T23:47:00.000Z",
      "season": 2026
    },
    {
      "name": "Keylen Davis",
      "position": "IOL",
      "origin": "Akron",
      "destination": "Pittsburgh",
      "rating": 0.85,
      "stars": 3,
      "eligibility": "Immediate",
      "transferDate": "2026-01-08T23:48:00.000Z",
      "season": 2026
    },
    {
      "name": "Alex Sanford Jr.",
      "position": "LB",
      "origin": "Purdue",
      "destination": "Pittsburgh",
      "rating": 0.86,
      "stars": 3,
      "eligibility": "Immediate",
      "transferDate": "2026-01-14T01:04:00.000Z",
      "season": 2026
    },
    {
      "name": "Eliyt Nairne",
      "position": "DL",
      "origin": "Tulane",
      "destination": "Pittsburgh",
      "rating": 0.85,
      "stars": 3,
      "eligibility": "Immediate",
      "transferDate": "2026-01-11T18:50:00.000Z",
      "season": 2026
    },
    {
      "name": "Gabe Russo",
      "position": "P",
      "origin": "Idaho State",
      "destination": "Pittsburgh",
      "rating": null,
      "stars": 2,
      "eligibility": "Immediate",
      "transferDate": "2026-01-09T23:43:00.000Z",
      "season": 2026
    },
    {
      "name": "Elijah Lagg",
      "position": "TE",
      "origin": "UAB",
      "destination": "Pittsburgh",
      "rating": 0.84,
      "stars": 3,
      "eligibility": "Immediate",
      "transferDate": "2026-01-10T23:40:00.000Z",
      "season": 2026
    },
    {
      "name": "Malik Knight",
      "position": "WR",
      "origin": "Western Carolina",
      "destination": "Pittsburgh",
      "rating": 0.83,
      "stars": 3,
      "eligibility": "Immediate",
      "transferDate": "2026-01-07T20:49:59.000Z",
      "season": 2026
    },
    {
      "name": "Netinho Olivieri",
      "position": "OT",
      "origin": "Pennsylvania",
      "destination": "Pittsburgh",
      "rating": 0.83,
      "stars": 3,
      "eligibility": "Immediate",
      "transferDate": "2026-01-04T17:58:00.000Z",
      "season": 2026
    },
    {
      "name": "Holden Geriner",
      "position": "QB",
      "origin": "Texas State",
      "destination": "Pittsburgh",
      "rating": 0.83,
      "stars": 3,
      "eligibility": "Immediate",
      "transferDate": "2026-01-16T22:49:00.000Z",
      "season": 2026
    }
  ]
}
