{
  "sourceId": "cfbd-context-v1",
  "sourceType": "context",
  "asOf": "2026-07-04",
  "version": "cfbd-2026.1",
  "team": "Texas A&M Aggies",
  "season": 2025,
  "provenance": {
    "sources": [
      {
        "name": "CFBD player/returning",
        "endpoint": "https://api.collegefootballdata.com/player/returning?year=2025&team=Texas%20A%26M"
      }
    ],
    "collectedAt": "2026-07-04T12:11:21.102Z",
    "collectorVersion": "e243f65",
    "dataSeason": 2025,
    "dataCutoff": null
  },
  "returningProduction": {
    "totalPPA": 302,
    "totalPassingPPA": 83.9,
    "totalReceivingPPA": 108.6,
    "totalRushingPPA": 109.5,
    "percentPPA": 0.753,
    "percentPassingPPA": 0.969,
    "percentReceivingPPA": 0.531,
    "percentRushingPPA": 0.993,
    "usage": 0.891,
    "passingUsage": 0.997,
    "receivingUsage": 0.551,
    "rushingUsage": 0.985
  }
}
