{
  "sourceId": "official-roster-v1",
  "sourceType": "official-roster",
  "team": "Ohio State Buckeyes",
  "sourceUrl": "https://ohiostatebuckeyes.com/sports/football/roster",
  "engine": "nuxt-sidearm",
  "degraded": false,
  "degradeReason": null,
  "coverage": 119,
  "provenance": {
    "sources": [
      {
        "name": "Official team roster page",
        "endpoint": "https://ohiostatebuckeyes.com/sports/football/roster"
      }
    ],
    "collectedAt": "2026-07-04T12:53:00.247Z",
    "collectorVersion": "b85b400",
    "dataSeason": 2026,
    "dataCutoff": null
  },
  "players": [
    {
      "name": "Brandon Inniss",
      "jersey": null,
      "position": "WR",
      "classYear": "Sr.",
      "hometown": "Hollywood, Fla.",
      "highSchool": null,
      "previousSchool": "American Heritage"
    },
    {
      "name": "Earl Little Jr.",
      "jersey": null,
      "position": "SAF",
      "classYear": "R-Sr.",
      "hometown": "Fort Lauderdale, Fla.",
      "highSchool": null,
      "previousSchool": "American Heritage"
    },
    {
      "name": "Legend Bey",
      "jersey": null,
      "position": "RB",
      "classYear": "Fr.",
      "hometown": "Forney, Texas",
      "highSchool": null,
      "previousSchool": "North Forney"
    },
    {
      "name": "Kenyatta Jackson Jr.",
      "jersey": null,
      "position": "DE",
      "classYear": "R-Sr.",
      "hometown": "Miami Gardens, Fla.",
      "highSchool": null,
      "previousSchool": "Chaminade-Madonna Prep"
    },
    {
      "name": "Devin McCuin",
      "jersey": null,
      "position": "WR",
      "classYear": "Sr.",
      "hometown": "Jacksonville, Texas",
      "highSchool": null,
      "previousSchool": "Jacksonville / UT San Antonio"
    },
    {
      "name": "James Smith",
      "jersey": null,
      "position": "DT",
      "classYear": "Sr.",
      "hometown": "Montgomery, Ala.",
      "highSchool": null,
      "previousSchool": "Carver / Alabama"
    },
    {
      "name": "Qua Russaw",
      "jersey": null,
      "position": "DE",
      "classYear": "R-Jr.",
      "hometown": "Montgomery, Ala.",
      "highSchool": null,
      "previousSchool": "Carver / Alabama"
    },
    {
      "name": "Jeremiah Smith",
      "jersey": null,
      "position": "WR",
      "classYear": "Jr.",
      "hometown": "Miami Gardens, Fla.",
      "highSchool": null,
      "previousSchool": "Chaminade-Madonna Prep"
    },
    {
      "name": "Kyle Parker",
      "jersey": null,
      "position": "WR",
      "classYear": "R-Jr.",
      "hometown": "Allen, Texas",
      "highSchool": null,
      "previousSchool": "Lovejoy / LSU"
    },
    {
      "name": "Riley Pettijohn",
      "jersey": null,
      "position": "LB",
      "classYear": "So.",
      "hometown": "McKinney, Texas",
      "highSchool": null,
      "previousSchool": "McKinney"
    },
    {
      "name": "Jerquaden Guilford",
      "jersey": null,
      "position": "WR",
      "classYear": "Fr.",
      "hometown": "Fort Wayne, Ind.",
      "highSchool": null,
      "previousSchool": "Northrop"
    },
    {
      "name": "Devin Sanchez",
      "jersey": null,
      "position": "CB",
      "classYear": "So.",
      "hometown": "Houston, Texas",
      "highSchool": null,
      "previousSchool": "North Shore"
    },
    {
      "name": "Phillip Bell",
      "jersey": null,
      "position": "WR",
      "classYear": "R-Fr.",
      "hometown": "Mission Viejo, Calif.",
      "highSchool": null,
      "previousSchool": "Mission Viejo"
    },
    {
      "name": "Jermaine Mathews Jr.",
      "jersey": null,
      "position": "CB",
      "classYear": "Sr.",
      "hometown": "Cincinnati, Ohio",
      "highSchool": null,
      "previousSchool": "Winton Woods"
    },
    {
      "name": "De’Zie Jones",
      "jersey": null,
      "position": "WR",
      "classYear": "R-Fr.",
      "hometown": "Wayne, N.J.",
      "highSchool": null,
      "previousSchool": "DePaul Catholic"
    },
    {
      "name": "Jaylen McClain",
      "jersey": null,
      "position": "SAF",
      "classYear": "Jr.",
      "hometown": "Rahway, N.J.",
      "highSchool": null,
      "previousSchool": "Seton Hall Prep"
    },
    {
      "name": "Zion Grady",
      "jersey": null,
      "position": "DE",
      "classYear": "So.",
      "hometown": "Enterprise, Ala.",
      "highSchool": null,
      "previousSchool": "Enterprise"
    },
    {
      "name": "Tavien St. Clair",
      "jersey": null,
      "position": "QB",
      "classYear": "R-Fr.",
      "hometown": "Bellefontaine, Ohio",
      "highSchool": null,
      "previousSchool": "Bellefontaine"
    },
    {
      "name": "Leroy Roker III",
      "jersey": null,
      "position": "SAF",
      "classYear": "R-So.",
      "hometown": "Fort Myers, Fla.",
      "highSchool": null,
      "previousSchool": "Bishop Verot"
    },
    {
      "name": "Julian Sayin",
      "jersey": null,
      "position": "QB",
      "classYear": "R-So.",
      "hometown": "Carlsbad, Calif.",
      "highSchool": null,
      "previousSchool": "Carlsbad / Alabama"
    },
    {
      "name": "Brock Boyd",
      "jersey": null,
      "position": "WR",
      "classYear": "Fr.",
      "hometown": "Southlake, Texas",
      "highSchool": null,
      "previousSchool": "Southlake Carroll"
    },
    {
      "name": "Terry Moore",
      "jersey": null,
      "position": "SAF",
      "classYear": "R-Sr.",
      "hometown": "Washington, N.C.",
      "highSchool": null,
      "previousSchool": "Washington / Duke"
    },
    {
      "name": "Beau Atkinson",
      "jersey": null,
      "position": "DE",
      "classYear": "R-Sr.",
      "hometown": "Raleigh, N.C.",
      "highSchool": null,
      "previousSchool": "North Carolina / Leesville Road"
    },
    {
      "name": "Luke Fahey",
      "jersey": null,
      "position": "QB",
      "classYear": "Fr.",
      "hometown": "Mission Viejo, Calif.",
      "highSchool": null,
      "previousSchool": "Mission Viejo"
    },
    {
      "name": "Miles Lockhart",
      "jersey": null,
      "position": "CB",
      "classYear": "R-So.",
      "hometown": "Chandler, Ariz.",
      "highSchool": null,
      "previousSchool": "Basha"
    },
    {
      "name": "Christian Alliegro",
      "jersey": null,
      "position": "LB",
      "classYear": "Sr.",
      "hometown": "Darien, Conn.",
      "highSchool": null,
      "previousSchool": "Avon Old Farms / Wisconsin"
    },
    {
      "name": "Chris Henry Jr.",
      "jersey": null,
      "position": "WR",
      "classYear": "Fr.",
      "hometown": "Santa Ana, Calif.",
      "highSchool": null,
      "previousSchool": "Mater Dei"
    },
    {
      "name": "Jordan Thomas",
      "jersey": null,
      "position": "CB",
      "classYear": "Fr.",
      "hometown": "Oradell, N.J.",
      "highSchool": null,
      "previousSchool": "Bergen Catholic"
    },
    {
      "name": "Blaine Bradford",
      "jersey": null,
      "position": "SAF",
      "classYear": "Fr.",
      "hometown": "Baton Rouge, La.",
      "highSchool": null,
      "previousSchool": "Baton Rouge Catholic"
    },
    {
      "name": "Justyn Martin",
      "jersey": null,
      "position": "QB",
      "classYear": "R-Sr.",
      "hometown": "Inglewood, Calif.",
      "highSchool": null,
      "previousSchool": "Inglewood / UCLA / Maryland"
    },
    {
      "name": "Tarvos \"TJ\" Alford",
      "jersey": null,
      "position": "LB",
      "classYear": "So.",
      "hometown": "Port Saint Lucie, Fla.",
      "highSchool": null,
      "previousSchool": "Vero Beach"
    },
    {
      "name": "Cam Calhoun",
      "jersey": null,
      "position": "CB",
      "classYear": "R-Jr.",
      "hometown": "Cincinnati, Ohio",
      "highSchool": null,
      "previousSchool": "Winton Woods / Michigan / Utah / Alabama"
    },
    {
      "name": "Kolton Stover",
      "jersey": null,
      "position": "QB",
      "classYear": "R-Fr.",
      "hometown": "Centerburg, Ohio",
      "highSchool": null,
      "previousSchool": "Highland"
    },
    {
      "name": "Brady Geibel",
      "jersey": null,
      "position": "QB",
      "classYear": "R-Fr.",
      "hometown": "Sugarcreek, Ohio",
      "highSchool": null,
      "previousSchool": "Garaway / Furman"
    },
    {
      "name": "Jordyn Woods",
      "jersey": null,
      "position": "CB",
      "classYear": "R-Fr.",
      "hometown": "Cartersville, Ga.",
      "highSchool": null,
      "previousSchool": "Cartersville"
    },
    {
      "name": "Cincere Johnson",
      "jersey": null,
      "position": "LB",
      "classYear": "Fr.",
      "hometown": "Cleveland, Ohio",
      "highSchool": "Glenville",
      "previousSchool": null
    },
    {
      "name": "Brenten \"Inky\" Jones",
      "jersey": null,
      "position": "SAF",
      "classYear": "R-Sr.",
      "hometown": "Steubenville, Ohio",
      "highSchool": null,
      "previousSchool": "Steubenville"
    },
    {
      "name": "Anthony “Turbo” Rogers",
      "jersey": null,
      "position": "RB",
      "classYear": "R-Fr.",
      "hometown": "Montgomery, Ala.",
      "highSchool": null,
      "previousSchool": "Carver"
    },
    {
      "name": "Nolan Baudo",
      "jersey": null,
      "position": "WR",
      "classYear": "R-Jr.",
      "hometown": "Chicago, Ill.",
      "highSchool": null,
      "previousSchool": "Marist"
    },
    {
      "name": "Garrett Stover",
      "jersey": null,
      "position": "LB",
      "classYear": "R-So.",
      "hometown": "Sunbury, Ohio",
      "highSchool": null,
      "previousSchool": "Big Walnut"
    },
    {
      "name": "Ja’Kobi Jackson",
      "jersey": null,
      "position": "RB",
      "classYear": "R-Sr.",
      "hometown": "Pensacola, Fla.",
      "highSchool": null,
      "previousSchool": "Pensacola Catholic / Florida"
    },
    {
      "name": "Dominick Kelly",
      "jersey": null,
      "position": "CB",
      "classYear": "So.",
      "hometown": "St. Petersburg, Fla.",
      "highSchool": null,
      "previousSchool": "IMG Academy / Georgia"
    },
    {
      "name": "Bo Jackson",
      "jersey": null,
      "position": "RB",
      "classYear": "So.",
      "hometown": "Cleveland, Ohio",
      "highSchool": null,
      "previousSchool": "Villa Angela-St. Joseph"
    },
    {
      "name": "Jay Timmons",
      "jersey": null,
      "position": "CB",
      "classYear": "Fr.",
      "hometown": "Gibsonia, Pa.",
      "highSchool": null,
      "previousSchool": "Pine-Richland"
    },
    {
      "name": "Payton Pierce",
      "jersey": null,
      "position": "LB",
      "classYear": "Jr.",
      "hometown": "Lucas, Texas",
      "highSchool": null,
      "previousSchool": "Lovejoy"
    },
    {
      "name": "Simeon Caldwell",
      "jersey": null,
      "position": "SAF",
      "classYear": "Fr.",
      "hometown": "Jacksonville, Fla.",
      "highSchool": null,
      "previousSchool": "The Bolles School"
    },
    {
      "name": "Stanley Jackson Jr.",
      "jersey": null,
      "position": "RB",
      "classYear": "R-So.",
      "hometown": "Westerville, Ohio",
      "highSchool": null,
      "previousSchool": "Marshall / Westerville North"
    },
    {
      "name": "Favour Akih",
      "jersey": null,
      "position": "RB",
      "classYear": "Fr.",
      "hometown": "Delaware, Ohio",
      "highSchool": null,
      "previousSchool": "Rutherford B. Hayes"
    },
    {
      "name": "Deshawn Stewart",
      "jersey": null,
      "position": "SAF",
      "classYear": "R-Fr.",
      "hometown": "Wayne, N.J.",
      "highSchool": null,
      "previousSchool": "DePaul Catholic"
    },
    {
      "name": "Khmari Bing",
      "jersey": null,
      "position": "SAF",
      "classYear": "Fr.",
      "hometown": "Baltimore, Md.",
      "highSchool": null,
      "previousSchool": "St. Francis Academy"
    },
    {
      "name": "Amari Valerio-Hudson",
      "jersey": null,
      "position": "WR",
      "classYear": "R-Fr.",
      "hometown": "Dublin, Ohio",
      "highSchool": null,
      "previousSchool": "Coffman"
    },
    {
      "name": "Kaden Gebhardt",
      "jersey": null,
      "position": "SAF",
      "classYear": "Fr.",
      "hometown": "Lewis Center, Ohio",
      "highSchool": null,
      "previousSchool": "Olentangy"
    },
    {
      "name": "Isaiah West",
      "jersey": null,
      "position": "RB",
      "classYear": "So.",
      "hometown": "Philadelphia, Pa.",
      "highSchool": null,
      "previousSchool": "St. Joseph’s Prep"
    },
    {
      "name": "Eli Lee",
      "jersey": null,
      "position": "LB",
      "classYear": "R-Fr.",
      "hometown": "Akron, Ohio",
      "highSchool": null,
      "previousSchool": "Archbishop Hoban"
    },
    {
      "name": "Ryan Seimetz",
      "jersey": null,
      "position": "WR",
      "classYear": "Fr.",
      "hometown": "Jackson, Ohio",
      "highSchool": "Jackson",
      "previousSchool": null
    },
    {
      "name": "Brennen Schramm",
      "jersey": null,
      "position": "WR",
      "classYear": "R-Jr.",
      "hometown": "Medina, Ohio",
      "highSchool": null,
      "previousSchool": "Medina"
    },
    {
      "name": "Khary Wilder",
      "jersey": null,
      "position": "DE",
      "classYear": "Fr.",
      "hometown": "Gardena, Calif.",
      "highSchool": null,
      "previousSchool": "Junipero Serra"
    },
    {
      "name": "Jaystin Gwinn",
      "jersey": null,
      "position": "SAF",
      "classYear": "R-Fr.",
      "hometown": "Westerville, Ohio",
      "highSchool": null,
      "previousSchool": "Westerville Central"
    },
    {
      "name": "CJ Sanna",
      "jersey": null,
      "position": "LB",
      "classYear": "Fr.",
      "hometown": "Lewis Center, Ohio",
      "highSchool": null,
      "previousSchool": "Olentangy"
    },
    {
      "name": "Zach Hayes",
      "jersey": null,
      "position": "LB",
      "classYear": "R-So.",
      "hometown": "LaGrange Park, Ill.",
      "highSchool": null,
      "previousSchool": "Nazareth Academy"
    },
    {
      "name": "Frankie McAllister",
      "jersey": null,
      "position": "TE",
      "classYear": "Fr.",
      "hometown": "Columbus, Ohio",
      "highSchool": "St. Francis DeSales",
      "previousSchool": null
    },
    {
      "name": "Eli Riggs",
      "jersey": null,
      "position": "LB",
      "classYear": "R-So.",
      "hometown": "Cincinnati, Ohio",
      "highSchool": null,
      "previousSchool": "Indian Hill"
    },
    {
      "name": "Glorien Gough",
      "jersey": null,
      "position": "DB",
      "classYear": "R-So.",
      "hometown": "Palos Verdes Estates, Calif.",
      "highSchool": null,
      "previousSchool": "Mater Dei"
    },
    {
      "name": "Braxton Rembert",
      "jersey": null,
      "position": "LB",
      "classYear": "Fr.",
      "hometown": "Hoschton, Ga.",
      "highSchool": null,
      "previousSchool": "Mill Creek"
    },
    {
      "name": "Joe McGuire",
      "jersey": null,
      "position": "P",
      "classYear": "R-Jr.",
      "hometown": "Melbourne, Australia",
      "highSchool": null,
      "previousSchool": "Prokick Australia"
    },
    {
      "name": "Brody Jenkins",
      "jersey": null,
      "position": "LS",
      "classYear": "Fr.",
      "hometown": "Madison, Ga.",
      "highSchool": "Morgan County",
      "previousSchool": null
    },
    {
      "name": "Amar’e Miller",
      "jersey": null,
      "position": "CB",
      "classYear": "Fr.",
      "hometown": "Pickerington, Ohio",
      "highSchool": null,
      "previousSchool": "Pickerington North"
    },
    {
      "name": "Epi Sitanilei",
      "jersey": null,
      "position": "DE",
      "classYear": "R-Fr.",
      "hometown": "Ontario, Calif.",
      "highSchool": null,
      "previousSchool": "St. John Bosco"
    },
    {
      "name": "Ryan Rudzinski",
      "jersey": null,
      "position": "SAF",
      "classYear": "R-Jr.",
      "hometown": "Columbus, Ohio",
      "highSchool": null,
      "previousSchool": "Bishop Watterson"
    },
    {
      "name": "Dalton Riggs",
      "jersey": null,
      "position": "LS",
      "classYear": "R-Sr.",
      "hometown": "Eagle, Idaho",
      "highSchool": null,
      "previousSchool": "Eagle / BYU / UCF"
    },
    {
      "name": "Marcello Diomede",
      "jersey": null,
      "position": "K",
      "classYear": "R-Jr.",
      "hometown": "Glen Ellyn, Ill.",
      "highSchool": "Glenbard West / Notre Dame",
      "previousSchool": null
    },
    {
      "name": "Gavin Thobe",
      "jersey": null,
      "position": "SAF",
      "classYear": "R-Fr.",
      "hometown": "Bellbrook, Ohio",
      "highSchool": null,
      "previousSchool": "Bellbrook"
    },
    {
      "name": "Alec DelSignore",
      "jersey": null,
      "position": "LB",
      "classYear": "R-Jr.",
      "hometown": "Youngstown, Ohio",
      "highSchool": null,
      "previousSchool": "Cardinal Mooney"
    },
    {
      "name": "Luke Montgomery",
      "jersey": null,
      "position": "OL",
      "classYear": "Sr.",
      "hometown": "Findlay, Ohio",
      "highSchool": null,
      "previousSchool": "Findlay"
    },
    {
      "name": "Ty Howard",
      "jersey": null,
      "position": "LB",
      "classYear": "R-Sr.",
      "hometown": "Cleveland, Ohio",
      "highSchool": null,
      "previousSchool": "Villa Angela-St. Joseph / Duquesne"
    },
    {
      "name": "Will Smith Jr.",
      "jersey": null,
      "position": "DT",
      "classYear": "R-Jr.",
      "hometown": "Dublin, Ohio",
      "highSchool": null,
      "previousSchool": "Coffman"
    },
    {
      "name": "Na'il Diggs Jr.",
      "jersey": null,
      "position": "LB",
      "classYear": "Fr.",
      "hometown": "Charlotte, N.C.",
      "highSchool": "Charlotte Latin",
      "previousSchool": null
    },
    {
      "name": "John Walker",
      "jersey": null,
      "position": "DT",
      "classYear": "R-Jr.",
      "hometown": "Kissimmee, Fla.",
      "highSchool": null,
      "previousSchool": "Osceola / UCF"
    },
    {
      "name": "Nate Riegle",
      "jersey": null,
      "position": "DE",
      "classYear": "R-So.",
      "hometown": "Findlay, Ohio",
      "highSchool": null,
      "previousSchool": "Findlay / Ohio U."
    },
    {
      "name": "Ian Gecse",
      "jersey": null,
      "position": "OL",
      "classYear": "R-Jr.",
      "hometown": "Grandview Heights, Ohio",
      "highSchool": null,
      "previousSchool": "Grandview"
    },
    {
      "name": "Gabe VanSickle",
      "jersey": null,
      "position": "OL",
      "classYear": "R-So.",
      "hometown": "Coopersville, Mich.",
      "highSchool": null,
      "previousSchool": "Coopersville"
    },
    {
      "name": "Ashton Yeager",
      "jersey": null,
      "position": "DT",
      "classYear": "R-Fr.",
      "hometown": "Findlay, Ohio",
      "highSchool": null,
      "previousSchool": "Findlay / Bowling Green"
    },
    {
      "name": "Jaxon Powell",
      "jersey": null,
      "position": "OL",
      "classYear": "Fr.",
      "hometown": "Portsmouth, Ohio",
      "highSchool": null,
      "previousSchool": "Northwest"
    },
    {
      "name": "Landon Beal",
      "jersey": null,
      "position": "LS",
      "classYear": "R-So.",
      "hometown": "Grove City, Ohio",
      "highSchool": null,
      "previousSchool": "Grove City / Maine"
    },
    {
      "name": "Joshua Padilla",
      "jersey": null,
      "position": "OL",
      "classYear": "R-Jr.",
      "hometown": "Huber Heights, Ohio",
      "highSchool": null,
      "previousSchool": "Wayne"
    },
    {
      "name": "Julian Goines-Jackson",
      "jersey": null,
      "position": "OL",
      "classYear": "R-Sr.",
      "hometown": "Zanesville, Ohio",
      "highSchool": null,
      "previousSchool": "Youngstown State / Zanesville"
    },
    {
      "name": "Simon Lorentz",
      "jersey": null,
      "position": "OL",
      "classYear": "R-So.",
      "hometown": "Dover, Ohio",
      "highSchool": null,
      "previousSchool": "Dover"
    },
    {
      "name": "Tucker Smith",
      "jersey": null,
      "position": "OL",
      "classYear": "Fr.",
      "hometown": "Phoenix, Ariz.",
      "highSchool": "Sandra Day O'Connor",
      "previousSchool": null
    },
    {
      "name": "Landry Brede",
      "jersey": null,
      "position": "OL",
      "classYear": "Fr.",
      "hometown": "Mentor, Ohio",
      "highSchool": null,
      "previousSchool": "Mentor"
    },
    {
      "name": "Austin Siereveld",
      "jersey": null,
      "position": "OL",
      "classYear": "R-Jr.",
      "hometown": "Liberty Township, Ohio",
      "highSchool": null,
      "previousSchool": "Lakota East"
    },
    {
      "name": "Mason Wilhelm",
      "jersey": null,
      "position": "OL",
      "classYear": "Fr.",
      "hometown": "Lakewood, Ohio",
      "highSchool": null,
      "previousSchool": "St. Edward"
    },
    {
      "name": "Ian Moore",
      "jersey": null,
      "position": "OL",
      "classYear": "R-So.",
      "hometown": "New Palestine, Ind.",
      "highSchool": null,
      "previousSchool": "New Palestine"
    },
    {
      "name": "Phillip Daniels",
      "jersey": null,
      "position": "OL",
      "classYear": "R-Jr.",
      "hometown": "Cincinnati, Ohio",
      "highSchool": null,
      "previousSchool": "Princeton / Minnesota"
    },
    {
      "name": "Deontae Armstrong",
      "jersey": null,
      "position": "OL",
      "classYear": "R-So.",
      "hometown": "Elyria, Ohio",
      "highSchool": null,
      "previousSchool": "St. Edward"
    },
    {
      "name": "Vasean Washington",
      "jersey": null,
      "position": "OL",
      "classYear": "R-Sr.",
      "hometown": "Springfield, Ohio",
      "highSchool": "Springfield / Dartmouth",
      "previousSchool": null
    },
    {
      "name": "Carter Lowe",
      "jersey": null,
      "position": "OL",
      "classYear": "R-Fr.",
      "hometown": "Toledo, Ohio",
      "highSchool": null,
      "previousSchool": "Whitmer"
    },
    {
      "name": "Carson Hinzman",
      "jersey": null,
      "position": "OL",
      "classYear": "R-Sr.",
      "hometown": "Spring Valley, Wis.",
      "highSchool": null,
      "previousSchool": "Saint Croix Central"
    },
    {
      "name": "Jake Cook",
      "jersey": null,
      "position": "OL",
      "classYear": "R-Fr.",
      "hometown": "Westerville, Ohio",
      "highSchool": null,
      "previousSchool": "Westerville North"
    },
    {
      "name": "Sam Greer",
      "jersey": null,
      "position": "OL",
      "classYear": "Fr.",
      "hometown": "Akron, Ohio",
      "highSchool": null,
      "previousSchool": "Archbishop Hoban"
    },
    {
      "name": "Max Riley",
      "jersey": null,
      "position": "OL",
      "classYear": "Fr.",
      "hometown": "Avon Lake, Ohio",
      "highSchool": null,
      "previousSchool": "Avon Lake"
    },
    {
      "name": "Jaeden Ricketts",
      "jersey": null,
      "position": "WR",
      "classYear": "Fr.",
      "hometown": "Pataskala, Ohio",
      "highSchool": null,
      "previousSchool": "Watkins Memorial"
    },
    {
      "name": "David Adolph",
      "jersey": null,
      "position": "WR",
      "classYear": "R-Sr.",
      "hometown": "Dublin, Ohio",
      "highSchool": null,
      "previousSchool": "Jerome"
    },
    {
      "name": "Nate Roberts",
      "jersey": null,
      "position": "TE",
      "classYear": "So.",
      "hometown": "Washington, Okla.",
      "highSchool": null,
      "previousSchool": "Washington"
    },
    {
      "name": "Hunter Welcing",
      "jersey": null,
      "position": "TE",
      "classYear": "R-Sr.",
      "hometown": "Deer Park, Ill.",
      "highSchool": null,
      "previousSchool": "Lake Zurich / Northwestern"
    },
    {
      "name": "Bennett Christian",
      "jersey": null,
      "position": "TE",
      "classYear": "R-Sr.",
      "hometown": "Acworth, Ga.",
      "highSchool": null,
      "previousSchool": "Allatoona"
    },
    {
      "name": "Mason Williams",
      "jersey": null,
      "position": "TE",
      "classYear": "Sr.",
      "hometown": "Mogadore, Ohio",
      "highSchool": null,
      "previousSchool": "Mogadore / Ohio U."
    },
    {
      "name": "Brody Lennon",
      "jersey": null,
      "position": "TE",
      "classYear": "R-Fr.",
      "hometown": "Cleveland, Ohio",
      "highSchool": null,
      "previousSchool": "Gilmour Academy"
    },
    {
      "name": "Maxence LeBlanc",
      "jersey": null,
      "position": "TE",
      "classYear": "R-So.",
      "hometown": "St-Bruno, Quebec",
      "highSchool": null,
      "previousSchool": "Baylor (Tenn.) School"
    },
    {
      "name": "Nick Lautar",
      "jersey": null,
      "position": "TE",
      "classYear": "Fr.",
      "hometown": "Lebanon, Ohio",
      "highSchool": null,
      "previousSchool": "Lebanon"
    },
    {
      "name": "Damari Simeon",
      "jersey": null,
      "position": "DT",
      "classYear": "Fr.",
      "hometown": "Richland, N.J.",
      "highSchool": null,
      "previousSchool": "St. Augustine Prep"
    },
    {
      "name": "Darryus McKinley",
      "jersey": null,
      "position": "DT",
      "classYear": "Fr.",
      "hometown": "Lafayette, La.",
      "highSchool": null,
      "previousSchool": "Acadiana"
    },
    {
      "name": "Cooper Peterson",
      "jersey": null,
      "position": "K",
      "classYear": "Fr.",
      "hometown": "Charlotte, N.C.",
      "highSchool": "Corvian Community",
      "previousSchool": null
    },
    {
      "name": "Brady Young",
      "jersey": null,
      "position": "P",
      "classYear": "R-Sr.",
      "hometown": "Perrysburg, Ohio",
      "highSchool": null,
      "previousSchool": "Perrysburg / Cincinnati / Houston Christian"
    },
    {
      "name": "Jason Moore",
      "jersey": null,
      "position": "DT",
      "classYear": "R-Jr.",
      "hometown": "Ft. Washington, Md.",
      "highSchool": null,
      "previousSchool": "DeMatha Catholic"
    },
    {
      "name": "Emanuel Ruffin",
      "jersey": null,
      "position": "DT",
      "classYear": "Fr.",
      "hometown": "Bessemer, Ala.",
      "highSchool": null,
      "previousSchool": "Bessemer City"
    },
    {
      "name": "Connor Hawkins",
      "jersey": null,
      "position": "K",
      "classYear": "R-So.",
      "hometown": "Liberty Hill, Texas",
      "highSchool": null,
      "previousSchool": "Liberty Hill / Baylor"
    },
    {
      "name": "Eddrick Houston",
      "jersey": null,
      "position": "DT",
      "classYear": "Jr.",
      "hometown": "Atlanta, Ga.",
      "highSchool": null,
      "previousSchool": "Buford"
    },
    {
      "name": "Dre Quinn",
      "jersey": null,
      "position": "DE",
      "classYear": "Fr.",
      "hometown": "Buford, Ga.",
      "highSchool": null,
      "previousSchool": "Buford"
    },
    {
      "name": "Jamir Perez",
      "jersey": null,
      "position": "DT",
      "classYear": "Fr.",
      "hometown": "Cleveland, Ohio",
      "highSchool": null,
      "previousSchool": "Glenville"
    }
  ]
}
