{
  "sourceId": "cfbd-context-v1",
  "sourceType": "context",
  "asOf": "2026-07-04",
  "version": "cfbd-2026.1",
  "team": "Georgia Bulldogs",
  "season": 2025,
  "provenance": {
    "sources": [
      {
        "name": "CFBD player/returning",
        "endpoint": "https://api.collegefootballdata.com/player/returning?year=2025&team=Georgia"
      }
    ],
    "collectedAt": "2026-07-04T12:11:44.750Z",
    "collectorVersion": "e243f65",
    "dataSeason": 2025,
    "dataCutoff": null
  },
  "returningProduction": {
    "totalPPA": 194.1,
    "totalPassingPPA": 25.9,
    "totalReceivingPPA": 143.2,
    "totalRushingPPA": 25,
    "percentPPA": 0.374,
    "percentPassingPPA": 0.159,
    "percentReceivingPPA": 0.504,
    "percentRushingPPA": 0.344,
    "usage": 0.392,
    "passingUsage": 0.169,
    "receivingUsage": 0.507,
    "rushingUsage": 0.57
  }
}
